universal_common_configuration/__init__.py
universal_common_configuration/abstractions.py
universal_common_configuration/environment_variables.py
universal_common_configuration/json.py
universal_common_configuration/user_secrets.py
universal_common_configuration-1.1.2.dist-info/METADATA
universal_common_configuration-1.1.2.dist-info/WHEEL
universal_common_configuration-1.1.2.dist-info/licenses/LICENSE
universal_common_configuration-1.1.2.dist-info/RECORD
