Metadata-Version: 2.3
Name: universal-common-configuration
Version: 1.1.2
Summary: A configuration management library inspired by Microsoft.Extensions.Configuration.
Author-email: Andrew Ong <ong.andrew@gmail.com>
License-File: LICENSE
Classifier: Development Status :: 3 - Alpha
Classifier: License :: CC0 1.0 Universal (CC0 1.0) Public Domain Dedication
Classifier: Operating System :: OS Independent
Classifier: Programming Language :: Python :: 3
Requires-Python: >=3.8
Requires-Dist: userpaths
